mdx_semanticwikilinks.py
setup.py
mdx_semanticwikilinks.egg-info/PKG-INFO
mdx_semanticwikilinks.egg-info/SOURCES.txt
mdx_semanticwikilinks.egg-info/dependency_links.txt
mdx_semanticwikilinks.egg-info/requires.txt
mdx_semanticwikilinks.egg-info/top_level.txt