Metadata-Version: 1.1
Name: mdx-semanticwikilinks
Version: 1.0
Summary: Python-Markdown extension to add support for semantic (wiki)links (RDFa)..
Home-page: http://activearchives.org/
Author: Alexandre Leray
Author-email: alexandre@stdin.fr
License: UNKNOWN
Platform: UNKNOWN
Classifier: Development Status :: 4 - Beta
Classifier: Operating System :: OS Independent
Classifier: License :: OSI Approved :: BSD License
Classifier: Intended Audience :: Developers
Classifier: Environment :: Web Environment
Classifier: Programming Language :: Python
Classifier: Topic :: Text Processing :: Filters
Classifier: Topic :: Text Processing :: Markup :: HTML
